{"@context":["https://www.w3.org/ns/did/v1","https://w3id.org/security/suites/jws-2020/v1"],"id":"did:web:tng-cdn-dev.who.int:v2:trustlist-ref:PH4H:CHL","controller":"did:web:tng-cdn-dev.who.int:v2:trustlist-ref:PH4H","verificationMethod":["did:web:tng-cdn-dev.who.int:v2:trustlist-ref:PH4H:CHL:SCA","did:web:tng-cdn-dev.who.int:v2:trustlist-ref:PH4H:CHL:DSC"],"proof":{"type":"JsonWebSignature2020","created":"2025-02-13T00:00:35Z","nonce":"3us4GEMZY5KHD7AgJfBlrXhXAnBKvU2r","proofPurpose":"assertionMethod","verificationMethod":"did:web:raw.githubusercontent.com:WorldHealthOrganization:tng-participants-dev:main:WHO:signing:DID","jws":"eyJiNjQiOmZhbHNlLCJjcml0IjpbImI2NCJdLCJhbGciOiJFUzI1NiJ9..MEUCIQC-28xPx-mzo7l-lifY5uAzA4C7Azp93LQr5dZH_O-vfgIgSFH5to_nhAF_bw_nLVFbv4-qXk-1t1ZzbzV8CfBbLa4"}}