{"@context":["https://www.w3.org/ns/did/v1","https://w3id.org/security/suites/jws-2020/v1"],"id":"did:web:tng-cdn-dev.who.int:v2:trustlist-ref:DCC:XU:SCA","controller":"did:web:tng-cdn-dev.who.int:v2:trustlist-ref:DCC:XU","verificationMethod":["did:web:tng-cdn-dev.who.int:v2:trustlist:DCC:XU:SCA"],"proof":{"type":"JsonWebSignature2020","created":"2025-07-12T12:00:35Z","nonce":"DjQVvqevnpkvYHno8iJ3nvsFO8qBuM7b","proofPurpose":"assertionMethod","verificationMethod":"did:web:raw.githubusercontent.com:WorldHealthOrganization:tng-participants-dev:main:WHO:signing:DID","jws":"eyJiNjQiOmZhbHNlLCJjcml0IjpbImI2NCJdLCJhbGciOiJFUzI1NiJ9..MEUCIB3OhcLmAdZDUE2W81X5cq4BaH6cDniEV3DRoct0l2NCAiEA0qUGw-GzBuLIpMA48ETaHQeYmWN20vVJ37BjwaTiE-A"}}