{"@context":["https://www.w3.org/ns/did/v1","https://w3id.org/security/suites/jws-2020/v1","https://worldhealthorganization.github.io/smart-trust/tng-additional-context/v1"],"id":"did:web:tng-cdn-dev.who.int:v2:trustlist-ref:-:XXK:SCA","controller":"did:web:tng-cdn-dev.who.int:v2:trustlist-ref:-:XXK","verificationMethod":["did:web:tng-cdn-dev.who.int:v2:trustlist:-:XXK:SCA"],"proof":{"type":"JsonWebSignature2020","created":"2025-10-18T18:00:42Z","nonce":"QcTE17NW25Eit9VeGWUJ8H4KEYSsNRy2","proofPurpose":"assertionMethod","verificationMethod":"did:web:raw.githubusercontent.com:WorldHealthOrganization:tng-participants-dev:main:WHO:signing:DID","jws":"eyJiNjQiOmZhbHNlLCJjcml0IjpbImI2NCJdLCJhbGciOiJFUzI1NiJ9..MEYCIQD8ZiRgY76uetfH9hQuje2Z-uR1OOcCeAw9nCqLSG43vAIhAKZGJ9Iyj9lCn9l5eU3CDc_FRi6VmWDxJyaeRzOth-SM"}}