{"@context":["https://www.w3.org/ns/did/v1","https://w3id.org/security/suites/jws-2020/v1","https://worldhealthorganization.github.io/smart-trust/tng-context/v1-DEV.jsonld"],"id":"did:web:tng-cdn-dev.who.int:v2:trustlist-ref:IPS-PILGRIMAGE:XXG:DESC","controller":"did:web:tng-cdn-dev.who.int:v2:trustlist-ref:IPS-PILGRIMAGE:XXG","verificationMethod":["did:web:tng-cdn-dev.who.int:v2:trustlist:IPS-PILGRIMAGE:XXG:DESC"],"proof":{"type":"JsonWebSignature2020","created":"2026-07-01T18:00:33Z","nonce":"dER9Bk2AKOaznsq9lZOHQ0LddLdKkJF3","proofPurpose":"assertionMethod","verificationMethod":"did:web:raw.githubusercontent.com:WorldHealthOrganization:tng-participants-dev:main:WHO:signing:DID","jws":"eyJiNjQiOmZhbHNlLCJjcml0IjpbImI2NCJdLCJhbGciOiJFUzI1NiJ9..MEUCIQDnqzQUirWE-m1wJzw_Zhp_qD3ffQgY7x0t31zjKD-xxwIgf6JgdsXl3XhEvRkXN9tKa3JObCxYpf9enjsjD02q4U0"}}