{"@context":["https://www.w3.org/ns/did/v1","https://w3id.org/security/suites/jws-2020/v1","https://worldhealthorganization.github.io/smart-trust/tng-additional-context/v2"],"id":"did:web:tng-cdn-dev.who.int:v2:trustlist-ref:PH4H:CHL:SCA","controller":"did:web:tng-cdn-dev.who.int:v2:trustlist-ref:PH4H:CHL","verificationMethod":["did:web:tng-cdn-dev.who.int:v2:trustlist:PH4H:CHL:SCA"],"proof":{"type":"JsonWebSignature2020","created":"2026-04-28T12:00:43Z","nonce":"zDpJzmzRaAfINDVIOIbBB2T6rqGXfZDc","proofPurpose":"assertionMethod","verificationMethod":"did:web:raw.githubusercontent.com:WorldHealthOrganization:tng-participants-dev:main:WHO:signing:DID","jws":"eyJiNjQiOmZhbHNlLCJjcml0IjpbImI2NCJdLCJhbGciOiJFUzI1NiJ9..MEUCIAwZRvJ6LELv7bS-IL_K5-Cro-9POX2jV7nW08rgwRtXAiEAgNzcgySI4MM74jw3RO3vUjKIL-SKDaZ8ROSgt2O479Y"}}