{"@context":["https://www.w3.org/ns/did/v1","https://w3id.org/security/suites/jws-2020/v1"],"id":"did:web:tng-cdn-dev.who.int:v2:trustlist-ref:PH4H:CHL:SCA","controller":"did:web:tng-cdn-dev.who.int:v2:trustlist-ref:PH4H:CHL","verificationMethod":["did:web:tng-cdn-dev.who.int:v2:trustlist:PH4H:CHL:SCA"],"proof":{"type":"JsonWebSignature2020","created":"2025-07-12T12:00:35Z","nonce":"0YC1QAzecejaculhe2ImAUmdaP2QTfkV","proofPurpose":"assertionMethod","verificationMethod":"did:web:raw.githubusercontent.com:WorldHealthOrganization:tng-participants-dev:main:WHO:signing:DID","jws":"eyJiNjQiOmZhbHNlLCJjcml0IjpbImI2NCJdLCJhbGciOiJFUzI1NiJ9..MEQCIG5SevXTfgNEwX4QD4DlkxKP-RHCsQXxzCbocIRHG7PTAiBUBbHZtvPsJF0uoeifarf8biFH2urW06j-Q7LYFn0ygg"}}