{"@context":["https://www.w3.org/ns/did/v1","https://w3id.org/security/suites/jws-2020/v1","https://worldhealthorganization.github.io/smart-trust/tng-additional-context/v1"],"id":"did:web:tng-cdn-dev.who.int:v2:trustlist-ref:PH4H:ECU","controller":"did:web:tng-cdn-dev.who.int:v2:trustlist-ref:PH4H","verificationMethod":["did:web:tng-cdn-dev.who.int:v2:trustlist-ref:PH4H:ECU:SCA","did:web:tng-cdn-dev.who.int:v2:trustlist-ref:PH4H:ECU:DSC"],"proof":{"type":"JsonWebSignature2020","created":"2026-03-02T06:00:23Z","nonce":"nmbYzfMMn9cVWUiZ8SK12OI9dv5db4mD","proofPurpose":"assertionMethod","verificationMethod":"did:web:raw.githubusercontent.com:WorldHealthOrganization:tng-participants-dev:main:WHO:signing:DID","jws":"eyJiNjQiOmZhbHNlLCJjcml0IjpbImI2NCJdLCJhbGciOiJFUzI1NiJ9..MEUCIFruYCgi60E3IEJlZHNQsuLIBcgXWFpq0EglZJg-MhvbAiEA4EuB-J640foPMkNG8kaResO4mbj46TDpjS_bbcnsJZ4"}}