{"@context":["https://www.w3.org/ns/did/v1","https://w3id.org/security/suites/jws-2020/v1"],"id":"did:web:worldhealthorganization.github.io:tng-cdn-dev:v2.0.0:trustlist-ref:RACSEL-DDVC:BLZ:DSC","controller":"did:web:worldhealthorganization.github.io:tng-cdn-dev:v2.0.0:trustlist-ref:RACSEL-DDVC:BLZ:DSC","verificationMethod":["did:web:worldhealthorganization.github.io:tng-cdn-dev:v2.0.0:trustlist:RACSEL-DDVC:BLZ:DSC#NX529J%2FHFsw%3D"],"proof":{"type":"JsonWebSignature2020","created":"2024-07-01T08:48:07Z","nonce":"ifIgshFgFJIcrGPWz3Q6QoBNn3upOFBC","proofPurpose":"assertionMethod","verificationMethod":"did:web:raw.githubusercontent.com:WorldHealthOrganization:tng-participants-dev:main:WHO:signing:DID","jws":"eyJiNjQiOmZhbHNlLCJjcml0IjpbImI2NCJdLCJhbGciOiJFUzI1NiJ9..MEQCIBGelpwZbPfqxw62G5AvBjdh4_oikS_fY3B2XT0H_GglAiAwFflqApY0yPa5LzVzzA7FaNCWyJ3kguxc23S83WfQPg"}}