{"@context":["https://www.w3.org/ns/did/v1","https://w3id.org/security/suites/jws-2020/v1"],"id":"did:web:worldhealthorganization.github.io:tng-cdn-dev:v2.0.0:trustlist-ref:-:HND:SCA","controller":"did:web:worldhealthorganization.github.io:tng-cdn-dev:v2.0.0:trustlist-ref:-:HND:SCA","verificationMethod":["did:web:worldhealthorganization.github.io:tng-cdn-dev:v2.0.0:trustlist:-:HND:SCA#TA7FfYsm528%3D"],"proof":{"type":"JsonWebSignature2020","created":"2024-07-01T08:48:07Z","nonce":"sihAFWVfjx7gjKZiKn73r9Rp1MPcAKqw","proofPurpose":"assertionMethod","verificationMethod":"did:web:raw.githubusercontent.com:WorldHealthOrganization:tng-participants-dev:main:WHO:signing:DID","jws":"eyJiNjQiOmZhbHNlLCJjcml0IjpbImI2NCJdLCJhbGciOiJFUzI1NiJ9..MEUCIBY7N55jFeah4aAkhj3a3M6xjbkVJ2_O5YcBj5wD7viUAiEAw07IZz3ke9nEG33znUBCjmt7-iip2WBckuSVAs65q5E"}}