{"@context":["https://www.w3.org/ns/did/v1","https://w3id.org/security/suites/jws-2020/v1"],"id":"did:web:worldhealthorganization.github.io:tng-cdn-dev:v2.0.0:trustlist-ref:DCC:-:DSC:NnUrZEg4ZmljSWM9","controller":"did:web:worldhealthorganization.github.io:tng-cdn-dev:v2.0.0:trustlist-ref:DCC:-:DSC:NnUrZEg4ZmljSWM9","verificationMethod":["did:web:worldhealthorganization.github.io:tng-cdn-dev:v2.0.0:trustlist:DCC:-:DSC:NnUrZEg4ZmljSWM9"],"proof":{"type":"JsonWebSignature2020","created":"2024-09-27T15:36:23Z","nonce":"23uqlWhIte2AUt3XauDFKPpYeuyu7wXx","proofPurpose":"assertionMethod","verificationMethod":"did:web:raw.githubusercontent.com:WorldHealthOrganization:tng-participants-dev:main:WHO:signing:DID","jws":"eyJiNjQiOmZhbHNlLCJjcml0IjpbImI2NCJdLCJhbGciOiJFUzI1NiJ9..MEQCIB7eYc5V7m9IFC44wvRlkv2Yyl_ivJg4pU4t7nhUAM8jAiBB-TTtNxyU6zEStuNzDKJxulHYkC-Iy2f3kDnPajSVoQ"}}