{"@context":["https://www.w3.org/ns/did/v1","https://w3id.org/security/suites/jws-2020/v1"],"id":"did:web:tng-cdn-dev.who.int:v2:trustlist-ref:-:XXB:DECA","controller":"did:web:tng-cdn-dev.who.int:v2:trustlist-ref:-:XXB","verificationMethod":["did:web:tng-cdn-dev.who.int:v2:trustlist:-:XXB:DECA"],"proof":{"type":"JsonWebSignature2020","created":"2025-06-15T18:00:22Z","nonce":"9OPnvK1ulfkIH6UF2AxOGKupszQxpgPn","proofPurpose":"assertionMethod","verificationMethod":"did:web:raw.githubusercontent.com:WorldHealthOrganization:tng-participants-dev:main:WHO:signing:DID","jws":"eyJiNjQiOmZhbHNlLCJjcml0IjpbImI2NCJdLCJhbGciOiJFUzI1NiJ9..MEYCIQCa-7wNtfKS1I-9kjmAl_0KR0BCfW6injD9MXavGZ6--AIhAIuJkVSH3BED8WUUkXTeseuOo7XGw7GKuKLgCT78kFL7"}}