{"@context":["https://www.w3.org/ns/did/v1","https://w3id.org/security/suites/jws-2020/v1"],"id":"did:web:tng-cdn-dev.who.int:v2:trustlist-ref:PH4H:ECU:SCA","controller":"did:web:tng-cdn-dev.who.int:v2:trustlist-ref:PH4H:ECU","verificationMethod":["did:web:tng-cdn-dev.who.int:v2:trustlist:PH4H:ECU:SCA"],"proof":{"type":"JsonWebSignature2020","created":"2026-05-05T18:00:47Z","nonce":"DyWoRCkdQXu0Z5VYyBsCqOzJlfN4JUa8","proofPurpose":"assertionMethod","verificationMethod":"did:web:raw.githubusercontent.com:WorldHealthOrganization:tng-participants-dev:main:WHO:signing:DID","jws":"eyJiNjQiOmZhbHNlLCJjcml0IjpbImI2NCJdLCJhbGciOiJFUzI1NiJ9..MEQCIFni2e-yI46jrTBc9AeSL8caZ9DGswMPZLRERt4qIAL-AiAs0YUIXmtpgvLmn3aJfUtq6Ck0Wb5plVyyXamynLTcnA"}}