{"@context":["https://www.w3.org/ns/did/v1","https://w3id.org/security/suites/jws-2020/v1","https://worldhealthorganization.github.io/smart-trust/tng-additional-context/v1"],"id":"did:web:tng-cdn-dev.who.int:v2:trustlist-ref:PH4H:ARG","controller":"did:web:tng-cdn-dev.who.int:v2:trustlist-ref:PH4H","verificationMethod":["did:web:tng-cdn-dev.who.int:v2:trustlist-ref:PH4H:ARG:SCA","did:web:tng-cdn-dev.who.int:v2:trustlist-ref:PH4H:ARG:DSC"],"proof":{"type":"JsonWebSignature2020","created":"2026-01-18T18:00:38Z","nonce":"tXW4dtV31YpRGfpwsKM5RpSuFQqaIxsg","proofPurpose":"assertionMethod","verificationMethod":"did:web:raw.githubusercontent.com:WorldHealthOrganization:tng-participants-dev:main:WHO:signing:DID","jws":"eyJiNjQiOmZhbHNlLCJjcml0IjpbImI2NCJdLCJhbGciOiJFUzI1NiJ9..MEUCIQCAOqVZvpRnPJhH1WPMlOXgZZrIf8eyzK50Lqvvr_hQZAIgB-8FvX97rkcoJpWM4O2PH1K5DT8dwsWLs89sPtklNzE"}}