{"@context":["https://www.w3.org/ns/did/v1","https://w3id.org/security/suites/jws-2020/v1","https://worldhealthorganization.github.io/smart-trust/tng-additional-context/v1"],"id":"did:web:tng-cdn-dev.who.int:v2:trustlist-ref:DCC:BLZ:SCA","controller":"did:web:tng-cdn-dev.who.int:v2:trustlist-ref:DCC:BLZ","verificationMethod":["did:web:tng-cdn-dev.who.int:v2:trustlist:DCC:BLZ:SCA"],"proof":{"type":"JsonWebSignature2020","created":"2026-03-30T12:00:40Z","nonce":"03kKldf6sv1pYBWJU9cpIuVXCglCiBK8","proofPurpose":"assertionMethod","verificationMethod":"did:web:raw.githubusercontent.com:WorldHealthOrganization:tng-participants-dev:main:WHO:signing:DID","jws":"eyJiNjQiOmZhbHNlLCJjcml0IjpbImI2NCJdLCJhbGciOiJFUzI1NiJ9..MEUCID-0l4eTk6Ax0Ca7OUhKUUiCowAVpznUDLFlL6LaVFeGAiEA5suQHJPNj72bhnyyAMfGPDNlrRzwh3xd9ImDcpCDjtM"}}