{"@context":["https://www.w3.org/ns/did/v1","https://w3id.org/security/suites/jws-2020/v1","https://worldhealthorganization.github.io/smart-trust/tng-additional-context/v1"],"id":"did:web:tng-cdn-dev.who.int:v2:trustlist-ref:-:XXC:SCA","controller":"did:web:tng-cdn-dev.who.int:v2:trustlist-ref:-:XXC","verificationMethod":["did:web:tng-cdn-dev.who.int:v2:trustlist:-:XXC:SCA"],"proof":{"type":"JsonWebSignature2020","created":"2026-01-11T12:00:39Z","nonce":"7uoL2z8QHjsVFJbOE8t535CvwxqJN61D","proofPurpose":"assertionMethod","verificationMethod":"did:web:raw.githubusercontent.com:WorldHealthOrganization:tng-participants-dev:main:WHO:signing:DID","jws":"eyJiNjQiOmZhbHNlLCJjcml0IjpbImI2NCJdLCJhbGciOiJFUzI1NiJ9..MEUCIQDZW9os1h-w3a6qzrwSxVyOkNGyptGC5bHxr17cKHwbnQIgXZbRqNDtoi2o1slwIbppa4Mzxl3vaA2_6cHX1OysGpM"}}