{"@context":["https://www.w3.org/ns/did/v1","https://w3id.org/security/suites/jws-2020/v1"],"id":"did:web:tng-cdn-dev.who.int:v2:trustlist-ref:DCC:XJ:DSC","controller":"did:web:tng-cdn-dev.who.int:v2:trustlist-ref:DCC:XJ","verificationMethod":["did:web:tng-cdn-dev.who.int:v2:trustlist:DCC:XJ:DSC"],"proof":{"type":"JsonWebSignature2020","created":"2025-06-07T12:00:34Z","nonce":"vnsGZrd8yKDanwnWVN25aSnXFzNGM34D","proofPurpose":"assertionMethod","verificationMethod":"did:web:raw.githubusercontent.com:WorldHealthOrganization:tng-participants-dev:main:WHO:signing:DID","jws":"eyJiNjQiOmZhbHNlLCJjcml0IjpbImI2NCJdLCJhbGciOiJFUzI1NiJ9..MEUCIBEND6wCl2ob2wN4mCKh4RcfzlMgeGZr3Bvzwq3XX3i-AiEA7Yp_x8mpYrDbjjnRvL_9SyPu9FwOJVW1eb79qQ28TnU"}}