{"@context":["https://www.w3.org/ns/did/v1","https://w3id.org/security/suites/jws-2020/v1"],"id":"did:web:tng-cdn-dev.who.int:v2:trustlist-ref:DCC:XCL","controller":"did:web:tng-cdn-dev.who.int:v2:trustlist-ref:DCC","verificationMethod":["did:web:tng-cdn-dev.who.int:v2:trustlist-ref:DCC:XCL:SCA","did:web:tng-cdn-dev.who.int:v2:trustlist-ref:DCC:XCL:DSC"],"proof":{"type":"JsonWebSignature2020","created":"2025-03-05T12:00:31Z","nonce":"zaz4KE7r9vuOR6nZYLJOM3cQIiNaSIH1","proofPurpose":"assertionMethod","verificationMethod":"did:web:raw.githubusercontent.com:WorldHealthOrganization:tng-participants-dev:main:WHO:signing:DID","jws":"eyJiNjQiOmZhbHNlLCJjcml0IjpbImI2NCJdLCJhbGciOiJFUzI1NiJ9..MEYCIQDRXNsHOz5nBEDq1sTO_f6MGTfMZWeyWiovlwv692TwSQIhAMvtGOV67CJE3RoH5y3PdmIrbPeMUotYn2hW1Z3cqThf"}}