{"@context":["https://www.w3.org/ns/did/v1","https://w3id.org/security/suites/jws-2020/v1","https://worldhealthorganization.github.io/smart-trust/tng-additional-context/v1"],"id":"did:web:tng-cdn-dev.who.int:v2:trustlist-ref:-:SLV:DSC","controller":"did:web:tng-cdn-dev.who.int:v2:trustlist-ref:-:SLV","verificationMethod":["did:web:tng-cdn-dev.who.int:v2:trustlist:-:SLV:DSC"],"proof":{"type":"JsonWebSignature2020","created":"2025-11-22T12:00:37Z","nonce":"Qbq3A7M44oP3fhDGOXHgjC4QdtCXtwjP","proofPurpose":"assertionMethod","verificationMethod":"did:web:raw.githubusercontent.com:WorldHealthOrganization:tng-participants-dev:main:WHO:signing:DID","jws":"eyJiNjQiOmZhbHNlLCJjcml0IjpbImI2NCJdLCJhbGciOiJFUzI1NiJ9..MEUCIAdg_UO2xbFrOjJ_g8DM9FfDaj1oyr76r8hZdxZyqw_bAiEAqwKiqKRdN6ypZ1Q_HTKEPoz8QOko-3M-FUfQlK2gyi4"}}