{"@context":["https://www.w3.org/ns/did/v1","https://w3id.org/security/suites/jws-2020/v1"],"id":"did:web:tng-cdn-dev.who.int:v2:trustlist-ref:-:PAN:DSC","controller":"did:web:tng-cdn-dev.who.int:v2:trustlist-ref:-:PAN","verificationMethod":["did:web:tng-cdn-dev.who.int:v2:trustlist:-:PAN:DSC"],"proof":{"type":"JsonWebSignature2020","created":"2025-05-07T00:00:47Z","nonce":"5pujokgG6Nt0gAIFJkvycvR9NVjrYmiB","proofPurpose":"assertionMethod","verificationMethod":"did:web:raw.githubusercontent.com:WorldHealthOrganization:tng-participants-dev:main:WHO:signing:DID","jws":"eyJiNjQiOmZhbHNlLCJjcml0IjpbImI2NCJdLCJhbGciOiJFUzI1NiJ9..MEUCIQC5rm-b-tcX6stiSbXZmOCTDxY-BUXBWQNdc2MaB7vCBAIgXsrxs1QjgDoafvBSIZj9TmLqKUErhill2R9JJXCUJis"}}