{"@context":["https://www.w3.org/ns/did/v1","https://w3id.org/security/suites/jws-2020/v1","https://worldhealthorganization.github.io/smart-trust/tng-additional-context/v1"],"id":"did:web:tng-cdn-dev.who.int:v2:trustlist-ref:DCC:DOM","controller":"did:web:tng-cdn-dev.who.int:v2:trustlist-ref:DCC","verificationMethod":["did:web:tng-cdn-dev.who.int:v2:trustlist-ref:DCC:DOM:DSC"],"proof":{"type":"JsonWebSignature2020","created":"2026-03-30T12:00:39Z","nonce":"OPpRvHToCk0oas8zmiQpYyFpwK8HvsMK","proofPurpose":"assertionMethod","verificationMethod":"did:web:raw.githubusercontent.com:WorldHealthOrganization:tng-participants-dev:main:WHO:signing:DID","jws":"eyJiNjQiOmZhbHNlLCJjcml0IjpbImI2NCJdLCJhbGciOiJFUzI1NiJ9..MEUCIDSgXiUKicW_zC44MdrgH7MWquPXpMGIRgL-B7wK2m0hAiEA_vJMCfSby0m9O7HMSKe6gYrkRh_lKm7lss353llxqaI"}}