{"@context":["https://www.w3.org/ns/did/v1","https://w3id.org/security/suites/jws-2020/v1","https://worldhealthorganization.github.io/smart-trust/tng-additional-context/v1"],"id":"did:web:tng-cdn-dev.who.int:v2:trustlist-ref:PH4H:XXF:DSC","controller":"did:web:tng-cdn-dev.who.int:v2:trustlist-ref:PH4H:XXF","verificationMethod":["did:web:tng-cdn-dev.who.int:v2:trustlist:PH4H:XXF:DSC"],"proof":{"type":"JsonWebSignature2020","created":"2025-11-12T12:00:38Z","nonce":"l7E6wP5bonP5F0o08GYOy7IA6Lg77Cji","proofPurpose":"assertionMethod","verificationMethod":"did:web:raw.githubusercontent.com:WorldHealthOrganization:tng-participants-dev:main:WHO:signing:DID","jws":"eyJiNjQiOmZhbHNlLCJjcml0IjpbImI2NCJdLCJhbGciOiJFUzI1NiJ9..MEYCIQCP5e4lt_k722_CnUC-lvy517PbWpkc5MyBw7ivmPc31QIhAOOQiR_Q_O1PmoGJXxPwTv2_LRK_8HwgwezYoqECFZpz"}}