{"@context":["https://www.w3.org/ns/did/v1","https://w3id.org/security/suites/jws-2020/v1"],"id":"did:web:tng-cdn-dev.who.int:v2:trustlist-ref:-:EST","controller":"did:web:tng-cdn-dev.who.int:v2:trustlist-ref:-","verificationMethod":["did:web:tng-cdn-dev.who.int:v2:trustlist-ref:-:EST:SCA"],"proof":{"type":"JsonWebSignature2020","created":"2025-09-13T12:00:21Z","nonce":"drykFMEM6tA8yhyvHOvWQVUoAc7dyzfc","proofPurpose":"assertionMethod","verificationMethod":"did:web:raw.githubusercontent.com:WorldHealthOrganization:tng-participants-dev:main:WHO:signing:DID","jws":"eyJiNjQiOmZhbHNlLCJjcml0IjpbImI2NCJdLCJhbGciOiJFUzI1NiJ9..MEQCIEk3aJ1GkfOrJYED-t5uKrdrxsIszK_wbBOL2L3Ip5KqAiBPk2VyaXc70adMnMvqcWxeNN3C2ibrXUF-mayHBAHJ5g"}}