{"@context":["https://www.w3.org/ns/did/v1","https://w3id.org/security/suites/jws-2020/v1"],"id":"did:web:tng-cdn-dev.who.int:v2:trustlist-ref:-:XE","controller":"did:web:tng-cdn-dev.who.int:v2:trustlist-ref:-","verificationMethod":["did:web:tng-cdn-dev.who.int:v2:trustlist-ref:-:XE:SCA","did:web:tng-cdn-dev.who.int:v2:trustlist-ref:-:XE:DSC"],"proof":{"type":"JsonWebSignature2020","created":"2025-02-17T06:00:36Z","nonce":"oqnNbnGDqtKojMJH1F9kkv7GiDIPTY2Y","proofPurpose":"assertionMethod","verificationMethod":"did:web:raw.githubusercontent.com:WorldHealthOrganization:tng-participants-dev:main:WHO:signing:DID","jws":"eyJiNjQiOmZhbHNlLCJjcml0IjpbImI2NCJdLCJhbGciOiJFUzI1NiJ9..MEUCIQCf0HqCo4ZW0hsTG1NF0QT1bN0894aB2HjC9boWwtQjlQIgMhuKaNXJJP1nYE-3BSoReo8HTyk7c4l3fxmAuoJtplQ"}}