{"@context":["https://www.w3.org/ns/did/v1","https://w3id.org/security/suites/jws-2020/v1"],"id":"did:web:tng-cdn-dev.who.int:v2:trustlist-ref:PH4H:XE:SCA","controller":"did:web:tng-cdn-dev.who.int:v2:trustlist-ref:PH4H:XE","verificationMethod":["did:web:tng-cdn-dev.who.int:v2:trustlist:PH4H:XE:SCA"],"proof":{"type":"JsonWebSignature2020","created":"2025-06-07T12:00:34Z","nonce":"4U27V2Dk3m4AlOyYqaig5khgvkSYTuUb","proofPurpose":"assertionMethod","verificationMethod":"did:web:raw.githubusercontent.com:WorldHealthOrganization:tng-participants-dev:main:WHO:signing:DID","jws":"eyJiNjQiOmZhbHNlLCJjcml0IjpbImI2NCJdLCJhbGciOiJFUzI1NiJ9..MEYCIQDobDOUo2rTa6hHI4x5mf8oJAxVWRMY6UpHIPTw-X8JZAIhAIDkwUFGcpruqSj4u8ZAvxeraG3tDJJIAhl03L5i8xvB"}}