{"@context":["https://www.w3.org/ns/did/v1","https://w3id.org/security/suites/jws-2020/v1"],"id":"did:web:tng-cdn-dev.who.int:v2:trustlist-ref:RACSEL-DDVC:BHS","controller":"did:web:tng-cdn-dev.who.int:v2:trustlist-ref:RACSEL-DDVC","verificationMethod":["did:web:tng-cdn-dev.who.int:v2:trustlist-ref:RACSEL-DDVC:BHS:SCA"],"proof":{"type":"JsonWebSignature2020","created":"2025-04-18T06:00:46Z","nonce":"coZE2dvgGkdYsyh98MbzyXVyN8QerSKO","proofPurpose":"assertionMethod","verificationMethod":"did:web:raw.githubusercontent.com:WorldHealthOrganization:tng-participants-dev:main:WHO:signing:DID","jws":"eyJiNjQiOmZhbHNlLCJjcml0IjpbImI2NCJdLCJhbGciOiJFUzI1NiJ9..MEQCIDqOk8Riu8ZtvVNYysto7jEqwCLRBMnzPgXSc1GVHrCHAiAQyV36wgf0Km4LcudiUDLfZ3sfeQ9V_w1ED03Oo7LloQ"}}