{"@context":["https://www.w3.org/ns/did/v1","https://w3id.org/security/suites/jws-2020/v1","https://worldhealthorganization.github.io/smart-trust/tng-context/v1-DEV.jsonld"],"id":"did:web:tng-cdn-dev.who.int:v2:trustlist-ref:-:SUR:DSC","controller":"did:web:tng-cdn-dev.who.int:v2:trustlist-ref:-:SUR","verificationMethod":["did:web:tng-cdn-dev.who.int:v2:trustlist:-:SUR:DSC"],"proof":{"type":"JsonWebSignature2020","created":"2026-07-01T18:00:34Z","nonce":"pFtoRNfJcAeNiRO29o2RJavmvPtsDPZ5","proofPurpose":"assertionMethod","verificationMethod":"did:web:raw.githubusercontent.com:WorldHealthOrganization:tng-participants-dev:main:WHO:signing:DID","jws":"eyJiNjQiOmZhbHNlLCJjcml0IjpbImI2NCJdLCJhbGciOiJFUzI1NiJ9..MEYCIQD2Yw1c1prk4ya_81as-fjtkLynqZZmEla6GtsmPSQVMgIhANiGwMDoEgx5wN_9BJOEZ9AtZy-kN_1AbYLx4VJ7u1yz"}}