{"@context":["https://www.w3.org/ns/did/v1","https://w3id.org/security/suites/jws-2020/v1","https://worldhealthorganization.github.io/smart-trust/tng-additional-context/v1"],"id":"did:web:tng-cdn-dev.who.int:v2:trustlist-ref:RACSEL-DDVC:ECU:SCA","controller":"did:web:tng-cdn-dev.who.int:v2:trustlist-ref:RACSEL-DDVC:ECU","verificationMethod":["did:web:tng-cdn-dev.who.int:v2:trustlist:RACSEL-DDVC:ECU:SCA"],"proof":{"type":"JsonWebSignature2020","created":"2025-11-12T12:00:38Z","nonce":"loNCbXKCgm7tdI2SmBfXImpyHrRjVvU2","proofPurpose":"assertionMethod","verificationMethod":"did:web:raw.githubusercontent.com:WorldHealthOrganization:tng-participants-dev:main:WHO:signing:DID","jws":"eyJiNjQiOmZhbHNlLCJjcml0IjpbImI2NCJdLCJhbGciOiJFUzI1NiJ9..MEUCICUdD094AIGSLCl_-x3cyvR1wxlzTZDrjv9-zD7O8Kn2AiEAjveDqbIBCXg_i5jC3lu4ht8ufc6iMtMoThu9mS7bfPA"}}