{"@context":["https://www.w3.org/ns/did/v1","https://w3id.org/security/suites/jws-2020/v1"],"id":"did:web:tng-cdn-dev.who.int:v2:trustlist-ref:PH4H:XF:SCA","controller":"did:web:tng-cdn-dev.who.int:v2:trustlist-ref:PH4H:XF","verificationMethod":["did:web:tng-cdn-dev.who.int:v2:trustlist:PH4H:XF:SCA"],"proof":{"type":"JsonWebSignature2020","created":"2025-01-23T12:00:17Z","nonce":"hlAsbLAYtisWiH22FusdCjMM5D02Ze2e","proofPurpose":"assertionMethod","verificationMethod":"did:web:raw.githubusercontent.com:WorldHealthOrganization:tng-participants-dev:main:WHO:signing:DID","jws":"eyJiNjQiOmZhbHNlLCJjcml0IjpbImI2NCJdLCJhbGciOiJFUzI1NiJ9..MEUCIQC_VIZRWZvZWSY7t2i3FDlZzss-KdEujHojjH6DysDppAIgIEyW7VOyPpW9iA9HjVjg6n7tk1ht17OxhPwNTIjqLWY"}}