{"@context":["https://www.w3.org/ns/did/v1","https://w3id.org/security/suites/jws-2020/v1"],"id":"did:web:worldhealthorganization.github.io:tng-cdn-dev:v2.0.0:trustlist-ref:DCC:ARM:SCA","controller":"did:web:worldhealthorganization.github.io:tng-cdn-dev:v2.0.0:trustlist-ref:DCC:ARM","verificationMethod":["did:web:worldhealthorganization.github.io:tng-cdn-dev:v2.0.0:trustlist:DCC:ARM:SCA"],"proof":{"type":"JsonWebSignature2020","created":"2024-10-25T00:00:32Z","nonce":"1M66l8RKRbW6yd5Clyra3bLDW01sijZm","proofPurpose":"assertionMethod","verificationMethod":"did:web:raw.githubusercontent.com:WorldHealthOrganization:tng-participants-dev:main:WHO:signing:DID","jws":"eyJiNjQiOmZhbHNlLCJjcml0IjpbImI2NCJdLCJhbGciOiJFUzI1NiJ9..MEQCIBT8-le8RcVUgdEJKw92_048s6jnwRB7BaYi1-NZH0VcAiASm5ondn9iaR8TZoyjpvuZHGoqhE7xdSVNHuMxtgRSyA"}}