{"@context":["https://www.w3.org/ns/did/v1","https://w3id.org/security/suites/jws-2020/v1"],"id":"did:web:tng-cdn-dev.who.int:v2:trustlist-ref:DCC:SGP","controller":"did:web:tng-cdn-dev.who.int:v2:trustlist-ref:DCC","verificationMethod":["did:web:tng-cdn-dev.who.int:v2:trustlist-ref:DCC:SGP:SCA","did:web:tng-cdn-dev.who.int:v2:trustlist-ref:DCC:SGP:DSC"],"proof":{"type":"JsonWebSignature2020","created":"2025-02-24T12:00:24Z","nonce":"10tjNEyhETwZ5J93flCMKWIcryGEep9v","proofPurpose":"assertionMethod","verificationMethod":"did:web:raw.githubusercontent.com:WorldHealthOrganization:tng-participants-dev:main:WHO:signing:DID","jws":"eyJiNjQiOmZhbHNlLCJjcml0IjpbImI2NCJdLCJhbGciOiJFUzI1NiJ9..MEQCIBpwrz6WQOeQ9RzAg6J7puP3Cb4tv76z77y5TIwgJ1teAiBrnnnatwJ5es6BkRz_1ZbxYbD9Yc7fnJdYAYEyM2_6mw"}}