{"@context":["https://www.w3.org/ns/did/v1","https://w3id.org/security/suites/jws-2020/v1","https://worldhealthorganization.github.io/smart-trust/tng-additional-context/v1"],"id":"did:web:tng-cdn-dev.who.int:v2:trustlist-ref:-:XCL:SCA","controller":"did:web:tng-cdn-dev.who.int:v2:trustlist-ref:-:XCL","verificationMethod":["did:web:tng-cdn-dev.who.int:v2:trustlist:-:XCL:SCA"],"proof":{"type":"JsonWebSignature2020","created":"2025-10-11T12:00:41Z","nonce":"kLZ6WA4hv0aDREQhDdFqvgV2Clcd0jiC","proofPurpose":"assertionMethod","verificationMethod":"did:web:raw.githubusercontent.com:WorldHealthOrganization:tng-participants-dev:main:WHO:signing:DID","jws":"eyJiNjQiOmZhbHNlLCJjcml0IjpbImI2NCJdLCJhbGciOiJFUzI1NiJ9..MEUCIQChpa4m9J8rifHNGvPRSllRxY9UOFWlbpXWeWtuPYUn8AIgXvDLyeS9L4NotSYLIUVa7vJQmilvqXHI1Awrliwk62g"}}