{"@context":["https://www.w3.org/ns/did/v1","https://w3id.org/security/suites/jws-2020/v1"],"id":"did:web:tng-cdn-dev.who.int:v2:trustlist:-:WHO","controller":"did:web:tng-cdn-dev.who.int:v2:trustlist:-","verificationMethod":[],"proof":{"type":"JsonWebSignature2020","created":"2024-12-19T18:00:00Z","nonce":"smhv701asvxvu2ryw8RyIaPZrkwfvC3g","proofPurpose":"assertionMethod","verificationMethod":"did:web:raw.githubusercontent.com:WorldHealthOrganization:tng-participants-dev:main:WHO:signing:DID","jws":"eyJiNjQiOmZhbHNlLCJjcml0IjpbImI2NCJdLCJhbGciOiJFUzI1NiJ9..MEYCIQCMh-BEHUnZ652DbFngfU1YUCHr-cTp2AJSdIxE9d9XQAIhAM8TAV-q1NwC2sWv7rSssZLDdAJLlZx1Jh1X-N2M2Ex1"}}