{"@context":["https://www.w3.org/ns/did/v1","https://w3id.org/security/suites/jws-2020/v1"],"id":"did:web:tng-cdn-dev.who.int:v2:trustlist-ref:-:SUR","controller":"did:web:tng-cdn-dev.who.int:v2:trustlist-ref:-","verificationMethod":["did:web:tng-cdn-dev.who.int:v2:trustlist-ref:-:SUR:SCA","did:web:tng-cdn-dev.who.int:v2:trustlist-ref:-:SUR:DSC"],"proof":{"type":"JsonWebSignature2020","created":"2025-05-17T06:00:31Z","nonce":"TXaJahmTG1eDk1K8CcrhVof8oM6zxpI8","proofPurpose":"assertionMethod","verificationMethod":"did:web:raw.githubusercontent.com:WorldHealthOrganization:tng-participants-dev:main:WHO:signing:DID","jws":"eyJiNjQiOmZhbHNlLCJjcml0IjpbImI2NCJdLCJhbGciOiJFUzI1NiJ9..MEUCIQC_eJFq4sKCt7DQmBGHlWjDtNWjAngL9oSZxYt0SCMzUwIgStUJvVBKayUG3ox4kUR0G2xERyDmSjq6FXhSHqxFKtE"}}