{"@context":["https://www.w3.org/ns/did/v1","https://w3id.org/security/suites/jws-2020/v1"],"id":"did:web:tng-cdn-dev.who.int:v2:trustlist-ref:-:BRA:DSC","controller":"did:web:tng-cdn-dev.who.int:v2:trustlist-ref:-:BRA","verificationMethod":["did:web:tng-cdn-dev.who.int:v2:trustlist:-:BRA:DSC"],"proof":{"type":"JsonWebSignature2020","created":"2024-12-08T06:00:28Z","nonce":"kL6MclMyAj4H8vY8IARPJXLoDHiKlTGI","proofPurpose":"assertionMethod","verificationMethod":"did:web:raw.githubusercontent.com:WorldHealthOrganization:tng-participants-dev:main:WHO:signing:DID","jws":"eyJiNjQiOmZhbHNlLCJjcml0IjpbImI2NCJdLCJhbGciOiJFUzI1NiJ9..MEYCIQC65_E09fL59pkqPCrdzfaJs1bVJgrWE6MOUFtFCKMq5AIhAIV2TNS86CT_BzcjcDo-duPr_js40Sy_iwhcCi6OVxA3"}}