{"@context":["https://www.w3.org/ns/did/v1","https://w3id.org/security/suites/jws-2020/v1"],"id":"did:web:tng-cdn-dev.who.int:v2:trustlist-ref:RACSEL-DDVC:ARG:SCA","controller":"did:web:tng-cdn-dev.who.int:v2:trustlist-ref:RACSEL-DDVC:ARG","verificationMethod":["did:web:tng-cdn-dev.who.int:v2:trustlist:RACSEL-DDVC:ARG:SCA"],"proof":{"type":"JsonWebSignature2020","created":"2025-02-24T12:00:29Z","nonce":"qvK1snbQk3rmYyfrlUPmKk8ZCc04htUo","proofPurpose":"assertionMethod","verificationMethod":"did:web:raw.githubusercontent.com:WorldHealthOrganization:tng-participants-dev:main:WHO:signing:DID","jws":"eyJiNjQiOmZhbHNlLCJjcml0IjpbImI2NCJdLCJhbGciOiJFUzI1NiJ9..MEYCIQCZ7Wbgsg0mpH4ZtnI_IDhIjmg-c5aIp9ldysbbWQfFvQIhAP3m0l2c4Di6_MaSNlovlenl6ZEobFxnGggYKxa8H3uI"}}