{"@context":["https://www.w3.org/ns/did/v1","https://w3id.org/security/suites/jws-2020/v1"],"id":"did:web:tng-cdn-dev.who.int:v2:trustlist-ref:DCC:HND","controller":"did:web:tng-cdn-dev.who.int:v2:trustlist-ref:DCC","verificationMethod":["did:web:tng-cdn-dev.who.int:v2:trustlist-ref:DCC:HND:DSC"],"proof":{"type":"JsonWebSignature2020","created":"2025-06-07T12:00:30Z","nonce":"8inXogY1xAdliv8pO0tlsoF7E7ZuVfOC","proofPurpose":"assertionMethod","verificationMethod":"did:web:raw.githubusercontent.com:WorldHealthOrganization:tng-participants-dev:main:WHO:signing:DID","jws":"eyJiNjQiOmZhbHNlLCJjcml0IjpbImI2NCJdLCJhbGciOiJFUzI1NiJ9..MEUCIEoqhxm5_y0cBxY7_6vmhgcci9TAANrUjti8YyCai4JcAiEA8i8M5s_zs_4i0CUS_ZXbhIDWEnox5xdGgPQ6iq-BMhA"}}