{"@context":["https://www.w3.org/ns/did/v1","https://w3id.org/security/suites/jws-2020/v1"],"id":"did:web:tng-cdn-dev.who.int:v2:trustlist-ref:-:TGO:SCA","controller":"did:web:tng-cdn-dev.who.int:v2:trustlist-ref:-:TGO","verificationMethod":["did:web:tng-cdn-dev.who.int:v2:trustlist:-:TGO:SCA"],"proof":{"type":"JsonWebSignature2020","created":"2025-01-23T12:00:18Z","nonce":"NISS6VFS0IV7CsE1ntnuS1Tc88RNsHk3","proofPurpose":"assertionMethod","verificationMethod":"did:web:raw.githubusercontent.com:WorldHealthOrganization:tng-participants-dev:main:WHO:signing:DID","jws":"eyJiNjQiOmZhbHNlLCJjcml0IjpbImI2NCJdLCJhbGciOiJFUzI1NiJ9..MEUCIEHNTjSBFmoepr6lPFG1NbLNlsKP8YMTDaVztYNq5e5wAiEA68e66ctNqd7tUsPL3vaGs5qwKT5fL-OEUq6asiCuGUQ"}}