{"@context":["https://www.w3.org/ns/did/v1","https://w3id.org/security/suites/jws-2020/v1"],"id":"did:web:tng-cdn-dev.who.int:v2:trustlist-ref:IPS-PILGRIMAGE:XU:DECA","controller":"did:web:tng-cdn-dev.who.int:v2:trustlist-ref:IPS-PILGRIMAGE:XU","verificationMethod":["did:web:tng-cdn-dev.who.int:v2:trustlist:IPS-PILGRIMAGE:XU:DECA"],"proof":{"type":"JsonWebSignature2020","created":"2025-05-07T00:00:45Z","nonce":"ZlSaZZj60ZR1nzIZxoC72Ycb3hheHi5f","proofPurpose":"assertionMethod","verificationMethod":"did:web:raw.githubusercontent.com:WorldHealthOrganization:tng-participants-dev:main:WHO:signing:DID","jws":"eyJiNjQiOmZhbHNlLCJjcml0IjpbImI2NCJdLCJhbGciOiJFUzI1NiJ9..MEQCICyZ23WJvrl4aj2r10L8g0LswtnPRPDrUI6PaAKMZWFLAiBOzTo29v_4978bG6Pf6xmhP9B-HnkONMqh4F7jcbg-Og"}}