{"@context":["https://www.w3.org/ns/did/v1","https://w3id.org/security/suites/jws-2020/v1"],"id":"did:web:tng-cdn-dev.who.int:v2:trustlist-ref:DCC:IOM","controller":"did:web:tng-cdn-dev.who.int:v2:trustlist-ref:DCC","verificationMethod":["did:web:tng-cdn-dev.who.int:v2:trustlist-ref:DCC:IOM:SCA","did:web:tng-cdn-dev.who.int:v2:trustlist-ref:DCC:IOM:DSC"],"proof":{"type":"JsonWebSignature2020","created":"2026-05-05T18:00:44Z","nonce":"GgSzgxctXuVqqpn2Uu3t1P8Ia1bECy4U","proofPurpose":"assertionMethod","verificationMethod":"did:web:raw.githubusercontent.com:WorldHealthOrganization:tng-participants-dev:main:WHO:signing:DID","jws":"eyJiNjQiOmZhbHNlLCJjcml0IjpbImI2NCJdLCJhbGciOiJFUzI1NiJ9..MEUCIBAZBHx7Dk16C6y0xBgN6noUcSJctTyjEc-1qyk0NaNHAiEA1ZI-18Tp1MgXmOhInBxUrdBZh3jYsBow-QT6amlh80g"}}