{"@context":["https://www.w3.org/ns/did/v1","https://w3id.org/security/suites/jws-2020/v1"],"id":"did:web:tng-cdn-dev.who.int:v2:trustlist-ref:IPS:-:DSC","controller":"did:web:tng-cdn-dev.who.int:v2:trustlist-ref:IPS:-","verificationMethod":["did:web:tng-cdn-dev.who.int:v2:trustlist:IPS:-:DSC"],"proof":{"type":"JsonWebSignature2020","created":"2025-02-17T06:00:39Z","nonce":"qCkjhrVKIlFEEXh8iugigZM3IvlAcDfh","proofPurpose":"assertionMethod","verificationMethod":"did:web:raw.githubusercontent.com:WorldHealthOrganization:tng-participants-dev:main:WHO:signing:DID","jws":"eyJiNjQiOmZhbHNlLCJjcml0IjpbImI2NCJdLCJhbGciOiJFUzI1NiJ9..MEYCIQDEt_lZIh2xTqyuo9CJ1ROLoQLuaveQNOQ-2y_M3OUaAgIhALqbt4KerIQBXL1qqBL6jcPQ7F0BHwqjSZLAWierhXX2"}}