{"@context":["https://www.w3.org/ns/did/v1","https://w3id.org/security/suites/jws-2020/v1","https://worldhealthorganization.github.io/smart-trust/tng-additional-context/v1"],"id":"did:web:tng-cdn-dev.who.int:v2:trustlist-ref:PH4H:BHS","controller":"did:web:tng-cdn-dev.who.int:v2:trustlist-ref:PH4H","verificationMethod":["did:web:tng-cdn-dev.who.int:v2:trustlist-ref:PH4H:BHS:SCA","did:web:tng-cdn-dev.who.int:v2:trustlist-ref:PH4H:BHS:DSC"],"proof":{"type":"JsonWebSignature2020","created":"2025-11-29T12:00:32Z","nonce":"GzD5z2ahV8FMzAWDh7hskYkn6PcJKMJ8","proofPurpose":"assertionMethod","verificationMethod":"did:web:raw.githubusercontent.com:WorldHealthOrganization:tng-participants-dev:main:WHO:signing:DID","jws":"eyJiNjQiOmZhbHNlLCJjcml0IjpbImI2NCJdLCJhbGciOiJFUzI1NiJ9..MEUCIGcNQ24CViZ__3Ml-Jv80jJaawUrLCMJa2_YzLvI-zDaAiEA2mHt0bvs0wOvk9q9EE4cNFWx07RmvfPyETi6paNDBBU"}}