{"@context":["https://www.w3.org/ns/did/v1","https://w3id.org/security/suites/jws-2020/v1"],"id":"did:web:tng-cdn-dev.who.int:v2:trustlist-ref:PH4H:XXA:DSC","controller":"did:web:tng-cdn-dev.who.int:v2:trustlist-ref:PH4H:XXA","verificationMethod":["did:web:tng-cdn-dev.who.int:v2:trustlist:PH4H:XXA:DSC"],"proof":{"type":"JsonWebSignature2020","created":"2025-01-29T00:00:20Z","nonce":"MWZmjF0GRXsjGwu4GLeFVq8P2jfCP0OY","proofPurpose":"assertionMethod","verificationMethod":"did:web:raw.githubusercontent.com:WorldHealthOrganization:tng-participants-dev:main:WHO:signing:DID","jws":"eyJiNjQiOmZhbHNlLCJjcml0IjpbImI2NCJdLCJhbGciOiJFUzI1NiJ9..MEUCIEbB4BOAOVpUq_pskRtA0Y7QN6eDdovoKoXa4UeE_NJ9AiEAsTlhU7kqFYwad3OdmuKo6qJ9JdI04UwN8jtkaKisRno"}}