{"@context":["https://www.w3.org/ns/did/v1","https://w3id.org/security/suites/jws-2020/v1"],"id":"did:web:tng-cdn-dev.who.int:v2:trustlist-ref:-:XH:SCA","controller":"did:web:tng-cdn-dev.who.int:v2:trustlist-ref:-:XH","verificationMethod":["did:web:tng-cdn-dev.who.int:v2:trustlist:-:XH:SCA"],"proof":{"type":"JsonWebSignature2020","created":"2025-06-07T12:00:36Z","nonce":"XpO6koNRlwDl0Fhf7FElbcstsWM35Zlp","proofPurpose":"assertionMethod","verificationMethod":"did:web:raw.githubusercontent.com:WorldHealthOrganization:tng-participants-dev:main:WHO:signing:DID","jws":"eyJiNjQiOmZhbHNlLCJjcml0IjpbImI2NCJdLCJhbGciOiJFUzI1NiJ9..MEQCIEyvLd2LJaxn_19QYJumfdPTSB4YvKDtbtuSXDzq-hvvAiBKVBrFMxrgO6TecF1JAOeLWDvxEkhq0JKko61o-bCpfA"}}