{"@context":["https://www.w3.org/ns/did/v1","https://w3id.org/security/suites/jws-2020/v1"],"id":"did:web:tng-cdn-dev.who.int:v2:trustlist-ref:RACSEL-DDVC:-","controller":"did:web:tng-cdn-dev.who.int:v2:trustlist-ref:RACSEL-DDVC","verificationMethod":["did:web:tng-cdn-dev.who.int:v2:trustlist-ref:RACSEL-DDVC:-:SCA","did:web:tng-cdn-dev.who.int:v2:trustlist-ref:RACSEL-DDVC:-:DSC"],"proof":{"type":"JsonWebSignature2020","created":"2025-03-29T17:30:14Z","nonce":"u8gLYaVkat1UIjXse0AXG6xYW623tGGi","proofPurpose":"assertionMethod","verificationMethod":"did:web:raw.githubusercontent.com:WorldHealthOrganization:tng-participants-dev:main:WHO:signing:DID","jws":"eyJiNjQiOmZhbHNlLCJjcml0IjpbImI2NCJdLCJhbGciOiJFUzI1NiJ9..MEUCIBEIzsVSA5SxHk-HYvSDihVpJF26ywG0NVUYBgev6Wq1AiEA_CIH60Opxujl_bx-_xo9X3gFR4tPjZRpsSYd_v5wuJo"}}