{"@context":["https://www.w3.org/ns/did/v1","https://w3id.org/security/suites/jws-2020/v1","https://worldhealthorganization.github.io/smart-trust/tng-context/v1-DEV.jsonld"],"id":"did:web:tng-cdn-dev.who.int:v2:trustlist-ref:-:XXK","controller":"did:web:tng-cdn-dev.who.int:v2:trustlist-ref:-","verificationMethod":["did:web:tng-cdn-dev.who.int:v2:trustlist-ref:-:XXK:SCA","did:web:tng-cdn-dev.who.int:v2:trustlist-ref:-:XXK:DSC"],"proof":{"type":"JsonWebSignature2020","created":"2026-07-01T18:00:33Z","nonce":"wCuttZb79aLquNtIjIeyE3eC9GeN7ZBP","proofPurpose":"assertionMethod","verificationMethod":"did:web:raw.githubusercontent.com:WorldHealthOrganization:tng-participants-dev:main:WHO:signing:DID","jws":"eyJiNjQiOmZhbHNlLCJjcml0IjpbImI2NCJdLCJhbGciOiJFUzI1NiJ9..MEYCIQCpc22r_Bp61WMoid9pglz0UkPCjB51micBfiRQm5njoQIhAN4xWfkqxC65_u0BWWhk3zrLuuXa4dIxjoD9KW2CAH_P"}}