{"@context":["https://www.w3.org/ns/did/v1","https://w3id.org/security/suites/jws-2020/v1"],"id":"did:web:tng-cdn-dev.who.int:v2:trustlist-ref:DCC:TGO:SCA","controller":"did:web:tng-cdn-dev.who.int:v2:trustlist-ref:DCC:TGO","verificationMethod":["did:web:tng-cdn-dev.who.int:v2:trustlist:DCC:TGO:SCA"],"proof":{"type":"JsonWebSignature2020","created":"2025-06-15T18:00:20Z","nonce":"GAvJGTeAGEiYugSrQenoPGLRV4FnsA1D","proofPurpose":"assertionMethod","verificationMethod":"did:web:raw.githubusercontent.com:WorldHealthOrganization:tng-participants-dev:main:WHO:signing:DID","jws":"eyJiNjQiOmZhbHNlLCJjcml0IjpbImI2NCJdLCJhbGciOiJFUzI1NiJ9..MEQCIAXhHpZl2C2upPuWOWwF26V2VFrHQsPKQpBVFan7dIVcAiBNJCfPm8AuFiGkHumswJw97GkMu9dPgQB4B_9r78M_aw"}}