{"@context":["https://www.w3.org/ns/did/v1","https://w3id.org/security/suites/jws-2020/v1","https://worldhealthorganization.github.io/smart-trust/tng-additional-context/v1"],"id":"did:web:tng-cdn-dev.who.int:v2:trustlist-ref:DCC:XP","controller":"did:web:tng-cdn-dev.who.int:v2:trustlist-ref:DCC","verificationMethod":["did:web:tng-cdn-dev.who.int:v2:trustlist-ref:DCC:XP:SCA"],"proof":{"type":"JsonWebSignature2020","created":"2025-09-23T06:00:20Z","nonce":"a7DTCwD8cHIS9BwetEcQQH9ZQay5pj0e","proofPurpose":"assertionMethod","verificationMethod":"did:web:raw.githubusercontent.com:WorldHealthOrganization:tng-participants-dev:main:WHO:signing:DID","jws":"eyJiNjQiOmZhbHNlLCJjcml0IjpbImI2NCJdLCJhbGciOiJFUzI1NiJ9..MEQCIDhno7Bkb2abJpnWACeaLKo2rvn5wcDY8kOtRFTP7eXhAiAujLwzaPtuA9U8FFWiwOZJ4EK2AaZCOXgTIevlCbwALg"}}