{"@context":["https://www.w3.org/ns/did/v1","https://w3id.org/security/suites/jws-2020/v1","https://worldhealthorganization.github.io/smart-trust/tng-additional-context/v1"],"id":"did:web:tng-cdn-dev.who.int:v2:trustlist-ref:-:SVN","controller":"did:web:tng-cdn-dev.who.int:v2:trustlist-ref:-","verificationMethod":["did:web:tng-cdn-dev.who.int:v2:trustlist-ref:-:SVN:SCA"],"proof":{"type":"JsonWebSignature2020","created":"2026-02-15T12:00:41Z","nonce":"A64fUOIn5tqDMawhT1Jd1kxSKi7NbiBF","proofPurpose":"assertionMethod","verificationMethod":"did:web:raw.githubusercontent.com:WorldHealthOrganization:tng-participants-dev:main:WHO:signing:DID","jws":"eyJiNjQiOmZhbHNlLCJjcml0IjpbImI2NCJdLCJhbGciOiJFUzI1NiJ9..MEYCIQCM58J00BeiIzdpbe07vCh9NhhdWilrti7Qqp2SqeS40wIhAO7pYtYuqz81D3uI6T_8xr0gVYMkuwB4D0esbEj9vqJ1"}}