{"@context":["https://www.w3.org/ns/did/v1","https://w3id.org/security/suites/jws-2020/v1"],"id":"did:web:tng-cdn-dev.who.int:v2:trustlist-ref:RACSEL-DDVC:USA","controller":"did:web:tng-cdn-dev.who.int:v2:trustlist-ref:RACSEL-DDVC","verificationMethod":["did:web:tng-cdn-dev.who.int:v2:trustlist-ref:RACSEL-DDVC:USA:SCA"],"proof":{"type":"JsonWebSignature2020","created":"2025-04-04T18:00:30Z","nonce":"DyuLeTYkOceBCZPfb5K2MpQRKGFUdumy","proofPurpose":"assertionMethod","verificationMethod":"did:web:raw.githubusercontent.com:WorldHealthOrganization:tng-participants-dev:main:WHO:signing:DID","jws":"eyJiNjQiOmZhbHNlLCJjcml0IjpbImI2NCJdLCJhbGciOiJFUzI1NiJ9..MEYCIQCzYF28eyAShB4iHoDyDTCJWOBGQ4iDLcyktUwpH5BQAAIhANbxt0QCyTpUb6odoB3j7zI9keBcoHCmJnvcymrPcnPI"}}