{"@context":["https://www.w3.org/ns/did/v1","https://w3id.org/security/suites/jws-2020/v1"],"id":"did:web:worldhealthorganization.github.io:tng-cdn-dev:v2.0.0:trustlist-ref:DCC:XX:SCA","controller":"did:web:worldhealthorganization.github.io:tng-cdn-dev:v2.0.0:trustlist-ref:DCC:XX","verificationMethod":["did:web:worldhealthorganization.github.io:tng-cdn-dev:v2.0.0:trustlist:DCC:XX:SCA"],"proof":{"type":"JsonWebSignature2020","created":"2024-10-24T12:00:29Z","nonce":"xAuEZs1d3XgdPtoUqgadtUpB1CaxWgHK","proofPurpose":"assertionMethod","verificationMethod":"did:web:raw.githubusercontent.com:WorldHealthOrganization:tng-participants-dev:main:WHO:signing:DID","jws":"eyJiNjQiOmZhbHNlLCJjcml0IjpbImI2NCJdLCJhbGciOiJFUzI1NiJ9..MEYCIQCcisg6eWIFmwMV1O48pU-qfqcCISsbU6mb3nJH-422cgIhAI1dZgXC3Y6_E4dmSrkL2z00XY1cQCk0zlz5gUSTt2IG"}}