{"@context":["https://www.w3.org/ns/did/v1","https://w3id.org/security/suites/jws-2020/v1"],"id":"did:web:tng-cdn-dev.who.int:v2:trustlist-ref:DCC:AND:SCA","controller":"did:web:tng-cdn-dev.who.int:v2:trustlist-ref:DCC:AND","verificationMethod":["did:web:tng-cdn-dev.who.int:v2:trustlist:DCC:AND:SCA"],"proof":{"type":"JsonWebSignature2020","created":"2026-05-05T18:00:46Z","nonce":"tkVqcI5tTPO6Pw3ytJnQgBnDkkShR5Up","proofPurpose":"assertionMethod","verificationMethod":"did:web:raw.githubusercontent.com:WorldHealthOrganization:tng-participants-dev:main:WHO:signing:DID","jws":"eyJiNjQiOmZhbHNlLCJjcml0IjpbImI2NCJdLCJhbGciOiJFUzI1NiJ9..MEQCIEWWI1rZGwZshihbgLwJAIirvtzq5xwER9Q3-tsGmizzAiBwz3xaA6mPZG3krD_-zd71NC6NnVJZscfQbG6DRY071g"}}