{"@context":["https://www.w3.org/ns/did/v1","https://w3id.org/security/suites/jws-2020/v1"],"id":"did:web:tng-cdn-dev.who.int:v2:trustlist-ref:-:XM","controller":"did:web:tng-cdn-dev.who.int:v2:trustlist-ref:-","verificationMethod":["did:web:tng-cdn-dev.who.int:v2:trustlist-ref:-:XM:SCA","did:web:tng-cdn-dev.who.int:v2:trustlist-ref:-:XM:DSC"],"proof":{"type":"JsonWebSignature2020","created":"2025-07-05T12:00:17Z","nonce":"l8BMKtf7L0O0yMdixbAUoEsFB4fCSoFH","proofPurpose":"assertionMethod","verificationMethod":"did:web:raw.githubusercontent.com:WorldHealthOrganization:tng-participants-dev:main:WHO:signing:DID","jws":"eyJiNjQiOmZhbHNlLCJjcml0IjpbImI2NCJdLCJhbGciOiJFUzI1NiJ9..MEUCIQCommZMxmIMjkzt49vLiC_xbE-4jhHz_OIV2Ir9gBJKvgIgL2i2Nd1aEoPE7tqwWwYII6BfRcZh9xUqWS7FT_1fIHk"}}