{"@context":["https://www.w3.org/ns/did/v1","https://w3id.org/security/suites/jws-2020/v1","https://worldhealthorganization.github.io/smart-trust/tng-context/v1-DEV.jsonld"],"id":"did:web:tng-cdn-dev.who.int:v2:trustlist-ref:-:BRB:SCA","controller":"did:web:tng-cdn-dev.who.int:v2:trustlist-ref:-:BRB","verificationMethod":["did:web:tng-cdn-dev.who.int:v2:trustlist:-:BRB:SCA"],"proof":{"type":"JsonWebSignature2020","created":"2026-07-01T18:00:34Z","nonce":"TAZyHnLBo6pnd84ch54TAvFE0ZgHgr4i","proofPurpose":"assertionMethod","verificationMethod":"did:web:raw.githubusercontent.com:WorldHealthOrganization:tng-participants-dev:main:WHO:signing:DID","jws":"eyJiNjQiOmZhbHNlLCJjcml0IjpbImI2NCJdLCJhbGciOiJFUzI1NiJ9..MEUCIGCBYl3LtWFEx6fCPr4F6rCYTcsvY9F_0RYJmEFldXphAiEAkuPY37sBCKR30OhXl6U8lc43gDjbE0HG96_F-HL_5QI"}}