{"@context":["https://www.w3.org/ns/did/v1","https://w3id.org/security/suites/jws-2020/v1","https://worldhealthorganization.github.io/smart-trust/tng-additional-context/v1"],"id":"did:web:tng-cdn-dev.who.int:v2:trustlist-ref:PH4H:COL:DSC","controller":"did:web:tng-cdn-dev.who.int:v2:trustlist-ref:PH4H:COL","verificationMethod":["did:web:tng-cdn-dev.who.int:v2:trustlist:PH4H:COL:DSC"],"proof":{"type":"JsonWebSignature2020","created":"2025-10-14T12:00:38Z","nonce":"8f2vEN8GUX7TqALF8bEemeqY7dAmT2s1","proofPurpose":"assertionMethod","verificationMethod":"did:web:raw.githubusercontent.com:WorldHealthOrganization:tng-participants-dev:main:WHO:signing:DID","jws":"eyJiNjQiOmZhbHNlLCJjcml0IjpbImI2NCJdLCJhbGciOiJFUzI1NiJ9..MEYCIQDcu7BnmyYfM6AcsGak70nVx3U2FMU_IQZK-54Zu-quYAIhAMGOEhQaSh1i30p3z_Fq-dfgbPLCD7I7Fz_crluuZLe1"}}