{"@context":["https://www.w3.org/ns/did/v1","https://w3id.org/security/suites/jws-2020/v1"],"id":"did:web:tng-cdn-dev.who.int:v2:trustlist-ref:-:XK:SCA","controller":"did:web:tng-cdn-dev.who.int:v2:trustlist-ref:-:XK","verificationMethod":["did:web:tng-cdn-dev.who.int:v2:trustlist:-:XK:SCA"],"proof":{"type":"JsonWebSignature2020","created":"2025-02-24T12:00:30Z","nonce":"FbGcgi2qXFY2zhlyCVT0HA9eZlXZL8kf","proofPurpose":"assertionMethod","verificationMethod":"did:web:raw.githubusercontent.com:WorldHealthOrganization:tng-participants-dev:main:WHO:signing:DID","jws":"eyJiNjQiOmZhbHNlLCJjcml0IjpbImI2NCJdLCJhbGciOiJFUzI1NiJ9..MEYCIQCE3HHFd49ri2qi9-YqBZFGUHh3f9uGSKembj_ZG_vG8AIhAO8l-v_vTBfJ5hFuB5N60if8IMTKDmKetakm0y4XTw6f"}}