{"@context":["https://www.w3.org/ns/did/v1","https://w3id.org/security/suites/jws-2020/v1"],"id":"did:web:tng-cdn-dev.who.int:v2:trustlist-ref:-:XK:SCA","controller":"did:web:tng-cdn-dev.who.int:v2:trustlist-ref:-:XK","verificationMethod":["did:web:tng-cdn-dev.who.int:v2:trustlist:-:XK:SCA"],"proof":{"type":"JsonWebSignature2020","created":"2025-03-05T12:00:38Z","nonce":"WNODrshgUHrNI0HT1qlYEJn3RMWQe8bh","proofPurpose":"assertionMethod","verificationMethod":"did:web:raw.githubusercontent.com:WorldHealthOrganization:tng-participants-dev:main:WHO:signing:DID","jws":"eyJiNjQiOmZhbHNlLCJjcml0IjpbImI2NCJdLCJhbGciOiJFUzI1NiJ9..MEQCIEvsIqSKPbF-Vl4KWz8PbVYVRK7wYOZbCSdEcFoKTUYSAiAu0CVY5hsdJf_3WtCyujBwBs-D62vG2VetGWFdWva40w"}}