{"@context":["https://www.w3.org/ns/did/v1","https://w3id.org/security/suites/jws-2020/v1"],"id":"did:web:tng-cdn-dev.who.int:v2:trustlist-ref:-:BRA:SCA","controller":"did:web:tng-cdn-dev.who.int:v2:trustlist-ref:-:BRA","verificationMethod":["did:web:tng-cdn-dev.who.int:v2:trustlist:-:BRA:SCA"],"proof":{"type":"JsonWebSignature2020","created":"2024-12-08T06:00:28Z","nonce":"fi4Xy51A3F8tG4IUqwJKwT8tEYM4UL11","proofPurpose":"assertionMethod","verificationMethod":"did:web:raw.githubusercontent.com:WorldHealthOrganization:tng-participants-dev:main:WHO:signing:DID","jws":"eyJiNjQiOmZhbHNlLCJjcml0IjpbImI2NCJdLCJhbGciOiJFUzI1NiJ9..MEUCIAkM2x0yzS1TLApUIhel4fWWE61_WGRjj_TcCeVOV4PFAiEAqwhMxe5IJ8fkkbZ4XyEA8JQoflugERxsWH3wXZvSKG0"}}